[{"authorName":"Md Sabbir Hossain","authorId":"UHWIlcuyb4SpugjiWnM0Pba4z8b2","content":"ASSALAMU ALAIKUM","imageUrl":null,"timestamp":"2025-12-15T21:46:57.691450","likes":["UHWIlcuyb4SpugjiWnM0Pba4z8b2","TZ3hMizDizg1lxg4UWflDG1mVhq2"],"commentCount":0,"comments":[],"id":"post_1765813617691"},{"authorName":"Nokibul Hasan Siam","authorId":"DEoJLrjkH9dQ4BBpapSAY9hRpka2","content":"​আসসালামু আলাইকুম।\n​আমরা আনন্দের সাথে জানাচ্ছি যে এই অ্যাপ্লিকেশনটি সম্পূর্ণরূপে আমাদের নিজস্ব ব্যবহারের জন্য তৈরি করা হয়েছে। আমাদের এই প্ল্যাটফর্মে আপনারা বিভিন্ন লেখা বা আর্টিকেল পোস্ট করতে পারবেন এবং সেখানে অন্য সদস্যরা মন্তব্য করার সুযোগ পাবেন। এই মুহূর্তে আমরা সরাসরি ছবি বা ভিডিও পোস্ট করার সুবিধা দিতে না পারায় আন্তরিকভাবে দুঃখিত, তবে এই ফিচারটি দ্রুত নিয়ে আসার জন্য আমরা কাজ করে চলেছি। বর্তমানে, আপনারা ছবির URL ব্যবহার করে ছবি আপলোড করতে পারবেন। আমরা সকল এডমিনের কাছে প্রত্যাশা করব যে কেউ যেন কর্তৃপক্ষের অনুমতি ছাড়া অন্য কাউকে Secret Code প্রদান না করেন এবং নিজ নিজ দায়িত্ব যথাযথভাবে পালন করেন। আপনাদের সকলের সমর্থন ও সহযোগিতার জন্য ধন্যবাদ। ভবিষ্যতে, আমরা এই অ্যাপ্লিকেশনটিকে অন্যান্য শ্রেণীর ব্যবহারকারী এবং শিক্ষামূলক প্রয়োজনের জন্যও উপযোগী করে গড়ে তোলার পরিকল্পনা করছি।","imageUrl":null,"timestamp":"2025-12-12T17:04:35.997840","likes":["cmYn8rv890RiJPrGaiWhDRAR4m63","EdLiftUNhPa8iRZ53Aj5zMrDGGg2","UHWIlcuyb4SpugjiWnM0Pba4z8b2"],"commentCount":0,"comments":[],"id":"post_1765537475997"}]